special_distributions
