Metadata-Version: 1.0
Name: special-distributions
Version: 1.2
Summary: special_distributions
Home-page: UNKNOWN
Author: Mohamed Osama
Author-email: UNKNOWN
License: UNKNOWN
Platform: UNKNOWN
